{
  "name": "paypal",
  "config": {
    "displayNameBO": "Paypal",
    "displayName": {
      "fr": "Paypal",
      "en": "Paypal"
    },
    "frontPosition": 20,
    "activated": 0,
    "displayConfigurationFields": [
      "displayName",
      "minAmount",
      "maxAmount",
      "countries",
      "merchantId",
      "buttonShape",
      "buttonColor",
      "buttonHeight",
      "bnpl"
    ],
    "countrySelectorReadOnly": 0,
    "currencySelectorReadOnly": 0,
    "forceBasket": 0,
    "buttonShape": "rect",
    "buttonColor": "white",
    "buttonHeight": "40",
    "buttonLabel" : "pay",
    "merchantId": "",
    "bnpl": true,
    "minAmount": {
      "EUR": 0
    },
    "maxAmount": {
      "EUR": false
    },
    "logo": "paypal.png"
  }
}